larder/__init__.py
larder/crude.py
larder/dog.py
larder-0.0.4.dist-info/licenses/LICENSE
larder-0.0.4.dist-info/METADATA
larder-0.0.4.dist-info/WHEEL
larder-0.0.4.dist-info/top_level.txt
larder-0.0.4.dist-info/RECORD
