Metadata-Version: 2.4
Name: larder
Version: 0.0.4
Summary: Connect functions to stores - fetch inputs & persist outputs
Home-page: https://github.com/i2mint/larder
License: mit
Platform: any
License-File: LICENSE
Requires-Dist: au
Requires-Dist: dol
Requires-Dist: i2
Provides-Extra: testing
Requires-Dist: pytest-asyncio; extra == "testing"
Dynamic: license-file
